<?xml version="1.0" encoding="utf-8"?>
<odoo>
    <!-- Menú Principal -->
    <menuitem id="menu_museos_root" name="Gestión Museos" sequence="10"/>
    
    <!-- Dashboard -->
    <!-- <menuitem id="menu_museos_dashboard" name="Dashboard" parent="menu_museos_root" sequence="10"
              action="action_museo_dashboard"/> -->
    
    <!-- Museos -->
    <menuitem id="menu_museos_museos" name="Museos" parent="menu_museos_root" sequence="10"
              action="action_museo_museo"/>
              
    <!-- Submenú de Gestión -->
    <menuitem id="menu_museos_gestion" name="Gestión" parent="menu_museos_root" sequence="20"/>

    <!-- Submenú de Actividades -->
    <menuitem id="menu_museos_actividades_root" name="Actividades" parent="menu_museos_root" sequence="30"/>

    <!-- Submenú de Informes -->
    <menuitem id="menu_museos_informes_root" name="Informes" parent="menu_museos_root" sequence="40"/>
    
    
    <!-- Objetos -->
    <menuitem id="menu_museos_objetos" name="Objetos" parent="menu_museos_gestion" sequence="20"
              action="action_museo_objeto"/>
    
    <!-- Historias de Barrios -->
    <menuitem id="menu_museos_historias" name="Historias de Barrios" parent="menu_museos_gestion" sequence="30"
              action="action_museo_historia_barrio"/>
    
    <!-- Convenios -->
    <menuitem id="menu_museos_convenios" name="Convenios" parent="menu_museos_gestion" sequence="40"
              action="action_museo_convenio"/>
    
    <!-- Trabajadores -->
    <menuitem id="menu_museos_trabajadores" name="Trabajadores" parent="menu_museos_gestion" sequence="50"
              action="action_museo_trabajadores"/>
    
    
    
    <!-- Actividades -->
    <menuitem id="menu_museos_actividades" name="Actividades" parent="menu_museos_actividades_root" sequence="10"
              action="action_museo_actividad"/>
    
    <!-- Calendario -->
    <menuitem id="menu_museos_calendario" name="Calendario" parent="menu_museos_actividades_root" sequence="20"
              action="action_museo_actividad"
              />
    
    <!-- Registro de Asistencia -->
    <menuitem id="menu_museos_asistencia" name="Registro de Asistencia" parent="menu_museos_actividades_root" sequence="30"
              action="action_museo_registro_asistencia"/>
    
    
    
    <!-- Informes Estadísticos -->
    <menuitem id="menu_museos_informes" name="Informes Estadísticos" parent="menu_museos_informes_root" sequence="10"
              action="action_museo_informe"/>
    
    <!-- Submenú de Herramientas -->
    <menuitem id="menu_museos_herramientas" name="Herramientas" parent="menu_museos_root" sequence="50"/>
    
    <!-- Importar Objetos -->
    <menuitem id="menu_museos_importar_objetos" name="Importar Objetos" parent="menu_museos_herramientas" sequence="10"
              action="action_museo_wizard_importar_objetos"/>
    
    <!-- Asignar Trabajadores -->
    <menuitem id="menu_museos_asignar_trabajadores" name="Asignar Trabajadores" parent="menu_museos_herramientas" sequence="20"
              action="action_museo_wizard_asignar_trabajadores"/>
    
    <!-- Informe Rápido -->
    <menuitem id="menu_museos_informe_rapido" name="Informe Rápido" parent="menu_museos_herramientas" sequence="30"
              action="action_museo_wizard_generar_informe"/>
    
    <!-- Configuración -->
    <menuitem id="menu_museos_configuracion" name="Configuración" parent="menu_museos_root" sequence="60"
              action="action_museo_config_settings"/>
</odoo>